personalitylinmult/__init__.py
personalitylinmult/computational_complexity/flops_gpu_experiment.py
personalitylinmult/computational_complexity/inference_experiment_cpu.py
personalitylinmult/computational_complexity/inference_experiment_gpu.py
personalitylinmult/computational_complexity/performance_metrics.py
personalitylinmult/computational_complexity/utils.py
personalitylinmult/computational_complexity/visualization.py
personalitylinmult/preprocess/mosei_acoustic.py
personalitylinmult/preprocess/mosei_preprocess.py
personalitylinmult/preprocess/mosei_textual.py
personalitylinmult/preprocess/mosei_visual.py
personalitylinmult/preprocess/mosi_acoustic.py
personalitylinmult/preprocess/mosi_preprocess.py
personalitylinmult/preprocess/mosi_textual.py
personalitylinmult/preprocess/mosi_visual.py
personalitylinmult-1.0.0.dist-info/METADATA
personalitylinmult-1.0.0.dist-info/WHEEL
personalitylinmult-1.0.0.dist-info/licenses/LICENSE
personalitylinmult-1.0.0.dist-info/RECORD
