Metadata-Version: 2.3
Name: personalitylinmult
Version: 1.0.0
Summary: PersonalityLinMulT: Transformer-based Big Five Automatic Personality Perception.
Project-URL: Documentation, https://github.com/fodorad/personalitylinmult#readme
Project-URL: Issues, https://github.com/fodorad/personalitylinmult/issues
Project-URL: Source, https://github.com/fodorad/personalitylinmult
Author-email: fodorad <foauaai@inf.elte.hu>
License-Expression: MIT
License-File: LICENSE
Keywords: app,bigfive,linear-complexity attention,multimodal,personality,transformer
Classifier: License :: OSI Approved :: MIT License
Classifier: Operating System :: OS Independent
Classifier: Programming Language :: Python :: 3
Requires-Python: >=3.11
Requires-Dist: linmult==1.3.5
Requires-Dist: toml==0.10.2
Requires-Dist: torch==2.4.1
Requires-Dist: torchaudio==2.4.1
Requires-Dist: torchvision==0.19.1
Requires-Dist: tqdm==4.66.5
Provides-Extra: all
Requires-Dist: exordium[video]; extra == 'all'
Requires-Dist: lightning==2.4.0; extra == 'all'
Requires-Dist: matplotlib==3.9.2; extra == 'all'
Requires-Dist: opencv-python==4.10.0.84; extra == 'all'
Requires-Dist: pandas==2.2.3; extra == 'all'
Provides-Extra: train
Requires-Dist: exordium[video]; extra == 'train'
Requires-Dist: lightning==2.4.0; extra == 'train'
Requires-Dist: matplotlib==3.9.2; extra == 'train'
Requires-Dist: opencv-python==4.10.0.84; extra == 'train'
Requires-Dist: pandas==2.2.3; extra == 'train'
